py_tunes/__init__.py
py_tunes/api.py
py_tunes/app.py
py_tunes/library.py
py_tunes/version.py
py_tunes-1.0b3.dist-info/DESCRIPTION.rst
py_tunes-1.0b3.dist-info/METADATA
py_tunes-1.0b3.dist-info/RECORD
py_tunes-1.0b3.dist-info/WHEEL
py_tunes-1.0b3.dist-info/eager_resources.txt
py_tunes-1.0b3.dist-info/metadata.json
py_tunes-1.0b3.dist-info/top_level.txt
py_tunes-1.0b3.dist-info/zip-safe
