Metadata-Version: 2.0
Name: py-tunes
Version: 1.0b3
Summary: A Python API for the iTunes application and music library
Home-page: https://github.com/roguePanda/itunes-remote
Author: Ben Navetta
Author-email: ben.navetta@gmail.com
License: MIT
Keywords: itunes osx
Platform: UNKNOWN
Classifier: Development Status :: 4 - Beta
Classifier: Intended Audience :: Developers
Classifier: Topic :: Multimedia :: Sound/Audio
Classifier: Topic :: Software Development :: Libraries
Classifier: License :: OSI Approved :: MIT License
Classifier: Operating System :: MacOS :: MacOS X
Classifier: Programming Language :: Python :: 2
Classifier: Programming Language :: Python :: 3
Classifier: Programming Language :: Objective C
Requires-Dist: appdirs (~=1.0)
Requires-Dist: enum34
Requires-Dist: pyobjc-framework-ScriptingBridge (~=3.0)
Requires-Dist: six (~=1.9)
Requires-Dist: sqlalchemy (~=1.0)
